email_verify/__init__.py
email_verify/admin.py
email_verify/apps.py
email_verify/decorators.py
email_verify/email_utils.py
email_verify/exceptions.py
email_verify/forms.py
email_verify/mixins.py
email_verify/models.py
email_verify/signals.py
email_verify/tests.py
email_verify/urls.py
email_verify/utils.py
email_verify/views.py
email_verify/migrations/0001_initial.py
email_verify/migrations/__init__.py
email_verify/migrations/__pycache__/0001_initial.cpython-311.pyc
email_verify/migrations/__pycache__/0002_customuser.cpython-311.pyc
email_verify/migrations/__pycache__/__init__.cpython-311.pyc
email_verify/static/css/email_verify_css.css
email_verify/templates/email_verify/base.html
email_verify/templates/email_verify/failure.html
email_verify/templates/email_verify/success.html
email_verify-0.1.10.dist-info/METADATA
email_verify-0.1.10.dist-info/WHEEL
email_verify-0.1.10.dist-info/top_level.txt
email_verify-0.1.10.dist-info/RECORD
