Metadata-Version: 2.1
Name: email-verify
Version: 0.1.10
Summary: Django app for e-mail verification on sign up
Author: can gologlu
Author-email: can@xn--glolu-jua30a.com
Requires-Dist: itsdangerous >=2.1.2
